hbrsamplemodule/__init__.py
hbrsamplemodule/add.py
hbrsamplemodule/subtract.py
hbrsamplemodule/extras/__init__.py
hbrsamplemodule/extras/divide.py
hbrsamplemodule/extras/multiply.py
hbrsamplemodule-0.0.3.dist-info/LICENSE
hbrsamplemodule-0.0.3.dist-info/METADATA
hbrsamplemodule-0.0.3.dist-info/WHEEL
hbrsamplemodule-0.0.3.dist-info/top_level.txt
hbrsamplemodule-0.0.3.dist-info/RECORD
