Metadata-Version: 2.1
Name: hbrsamplemodule
Version: 0.0.3
Summary: My first Python package
Home-page: https://github.com/pypa/sampleproject
Author: Paul Huang
Author-email: 67788015@qq.com
License: UNKNOWN
Project-URL: Bug Tracker, https://github.com/pypa/sampleproject/issues
Keywords: python,first package
Platform: UNKNOWN
Classifier: Development Status :: 3 - Alpha
Classifier: Intended Audience :: Education
Classifier: Programming Language :: Python :: 2
Classifier: Programming Language :: Python :: 3
Classifier: Operating System :: MacOS :: MacOS X
Classifier: Operating System :: Microsoft :: Windows
Requires-Python: >=3.6
License-File: LICENSE
